frame2package/Frame2Package.py
frame2package/__init__.py
frame2package-0.0.3.dist-info/METADATA
frame2package-0.0.3.dist-info/WHEEL
frame2package-0.0.3.dist-info/top_level.txt
frame2package-0.0.3.dist-info/RECORD
