Metadata-Version: 2.1
Name: frame2package
Version: 0.0.3
Summary: Pandas dataframes to DDF packages.
Home-page: UNKNOWN
Author: Robin Linderborg
Author-email: robin@datastory.org
License: UNKNOWN
Download-URL: https://github.com/datastory-org/frame2package/archive/0.0.3.tar.gz
Platform: UNKNOWN
Requires-Dist: pandas (>=0.23)
Requires-Dist: ddf-utils (==0.6.2)
